ovos_ocp_youtube_plugin/__init__.py
ovos_ocp_youtube_plugin/config.py
ovos_ocp_youtube_plugin/version.py
ovos_ocp_youtube_plugin-0.0.6.dist-info/licenses/LICENSE
ovos_ocp_youtube_plugin-0.0.6.dist-info/METADATA
ovos_ocp_youtube_plugin-0.0.6.dist-info/WHEEL
ovos_ocp_youtube_plugin-0.0.6.dist-info/entry_points.txt
ovos_ocp_youtube_plugin-0.0.6.dist-info/top_level.txt
ovos_ocp_youtube_plugin-0.0.6.dist-info/zip-safe
ovos_ocp_youtube_plugin-0.0.6.dist-info/RECORD
