Metadata-Version: 2.4
Name: ovos_ocp_youtube_plugin
Version: 0.0.6
Summary: OCP youtube stream extractor plugin
Home-page: https://github.com/OpenVoiceOS/ovos-ocp-youtube-plugin
Author: JarbasAi
Author-email: jarbasai@mailfence.com
License: Apache-2.0
Keywords: ovos ocp plugin
License-File: LICENSE
Requires-Dist: ovos-plugin-manager<3.0.0,>=0.0.1
Requires-Dist: tutubo<3.0.0,>=2.0.2
Requires-Dist: yt-dlp
Dynamic: author
Dynamic: author-email
Dynamic: home-page
Dynamic: keywords
Dynamic: license
Dynamic: license-file
Dynamic: requires-dist
Dynamic: summary
